{
  "teachers": [
    {
      "id": 2,
      "avatar_url": "https://upload.wikimedia.org/wikipedia/commons/3/39/GodfreyKneller-IsaacNewton-1689.jpg",
      "name": "Isaac Newton",
      "birth": -10318838400000,
      "graduation": "doutorado",
      "modalidade": "P",
      "created_at": 1585860655657,
      "subjects": "Física, Matemática, Astronomia "
    },
    {
      "id": 3,
      "avatar_url": "https://upload.wikimedia.org/wikipedia/commons/c/cc/Galileo.arp.300pix.jpg",
      "name": "Galileu Galilei",
      "birth": -12808281600000,
      "graduation": "mestrado",
      "modalidade": "D",
      "created_at": 1585860761465,
      "subjects": "Física, Matemática, Filosofia"
    }
  ]
}